quas_docs/__init__.py
quas_docs/config.py
quas_docs/core.py
quas_docs/responses.py
quas_docs-0.1.2.dist-info/METADATA
quas_docs-0.1.2.dist-info/WHEEL
quas_docs-0.1.2.dist-info/top_level.txt
quas_docs-0.1.2.dist-info/RECORD
