Metadata-Version: 2.4
Name: quas-docs
Version: 0.1.2
Summary: A powerful, reusable package for generating comprehensive OpenAPI documentation with Flask-Pydantic-Spec
Home-page: https://github.com/zeddyemy/quas-docs
Author: Emmanuel Olowu
Author-email: Emmanuel Olowu <zeddyemy@gmail.com>
License: MIT
Keywords: flask,openapi,swagger,documentation,api,pydantic
Classifier: Development Status :: 4 - Beta
Classifier: Intended Audience :: Developers
Classifier: License :: OSI Approved :: MIT License
Classifier: Operating System :: OS Independent
Classifier: Programming Language :: Python :: 3
Classifier: Programming Language :: Python :: 3.12
Classifier: Framework :: Flask
Classifier: Topic :: Documentation
Classifier: Topic :: Software Development :: Libraries :: Python Modules
Classifier: Topic :: Internet :: WWW/HTTP :: Dynamic Content
Requires-Python: >=3.12
Requires-Dist: flask>=2.0.0
Requires-Dist: pydantic>=2.0.0
Requires-Dist: flask-pydantic-spec>=0.8.6
Dynamic: author
Dynamic: home-page
Dynamic: requires-python
